epochly/bootstrap.py
epochly/performance_config.py
epochly/config.py
epochly/diagnostics.py
epochly/__init__.py
epochly/py.typed
epochly/compatibility/aws_telemetry_client.py
epochly/compatibility/api_backend.py
epochly/compatibility/supervisor.py
epochly/compatibility/registry.py
epochly/compatibility/analyzer.py
epochly/compatibility/resource_manager.py
epochly/compatibility/__init__.py
epochly/compatibility/local_storage.py
epochly/compatibility/telemetry_streaming.py
epochly/compatibility/secure_node_auth.py
epochly/compatibility/cloud_sync.py
epochly/compatibility/subprocess_safety.py
epochly/compatibility/static_analyzer.py
epochly/compatibility/dynamodb_backend.py
epochly/compatibility/non_blocking_registry.py
epochly/compatibility/platform_safety.py
epochly/compatibility/telemetry_aggregator.py
epochly/compatibility/non_blocking_analyzer.py
epochly/compatibility/lstm_predictor.py
epochly/enhancement/capability_manifest.py
epochly/enhancement/detection_async.py
epochly/enhancement/compatibility_analyzer.py
epochly/enhancement/__init__.py
epochly/enhancement/ebpf_probes.py
epochly/enhancement/adaptive_thresholds.py
epochly/enhancement/argument_sizer.py
epochly/enhancement/workload_manifest.py
epochly/enhancement/decorators.py
epochly/hardware/counter_stream.py
epochly/gpu/topology_cache.py
epochly/gpu/licensing_cache.py
epochly/gpu/gpu_detector.py
epochly/gpu/gpu_diagnostics.py
epochly/gpu/__init__.py
epochly/gpu/gpu_algorithms.cpython-311-darwin.so
epochly/gpu/offload_optimizer.py
epochly/gpu/gpu_memory_manager.py
epochly/gpu/gpu_refresh_scheduler.py
epochly/gpu/intelligent_memory.py
epochly/gpu/cupy_manager.py
epochly/gpu/backend_registry.py
epochly/gpu/async_gpu_detector.py
epochly/core/prewarm.py
epochly/core/state_manager.py
epochly/core/signature_helper.py
epochly/core/progression_detector.py
epochly/core/resource_limiter.py
epochly/core/executor_registry.py
epochly/core/epochly_core.py
epochly-0.1.1.dist-info/RECORD
epochly-0.1.1.dist-info/WHEEL
epochly-0.1.1.dist-info/entry_points.txt
epochly-0.1.1.dist-info/top_level.txt
epochly-0.1.1.dist-info/METADATA
epochly-0.1.1.dist-info/licenses/LICENSE
