Metadata-Version: 2.4
Name: epochly
Version: 0.1.1
Summary: Epochly - Transparent performance optimization for Python applications
Home-page: https://epochly.com
Author: Epochly Development Team
Author-email: Epochly Development Team <dev@epochly-python.org>
License: EPOCHLY PROPRIETARY SOFTWARE LICENSE
Project-URL: Homepage, https://epochly.com
Project-URL: Documentation, https://epochly.com/docs
Project-URL: Repository, https://github.com/epochly-python/epochly.git
Project-URL: Bug Tracker, https://github.com/epochly-python/epochly/issues
Classifier: Development Status :: 3 - Alpha
Classifier: Intended Audience :: Developers
Classifier: License :: Other/Proprietary License
Classifier: Operating System :: OS Independent
Classifier: Programming Language :: Python :: 3
Classifier: Programming Language :: Python :: 3.9
Classifier: Programming Language :: Python :: 3.10
Classifier: Programming Language :: Python :: 3.11
Classifier: Programming Language :: Python :: 3.12
Classifier: Programming Language :: Python :: 3.13
Classifier: Topic :: Software Development :: Libraries :: Python Modules
Classifier: Topic :: System :: Distributed Computing
Classifier: Topic :: Scientific/Engineering
Requires-Python: >=3.8
License-File: LICENSE
Requires-Dist: psutil>=5.8.0
Requires-Dist: packaging>=20.0
Requires-Dist: numpy<1.27.0,>=1.20.0; python_version == "3.9"
Requires-Dist: numpy<1.27.0,>=1.21.0; python_version == "3.10"
Requires-Dist: numpy<1.27.0,>=1.22.0; python_version == "3.11"
Requires-Dist: numpy<1.27.0,>=1.23.0; python_version == "3.12"
Requires-Dist: numpy>=2.1.0; python_version >= "3.13"
Requires-Dist: cryptography<41,>=40.0.0; python_version < "3.10"
Requires-Dist: cryptography>=45.0.0; python_version >= "3.10"
Requires-Dist: pybind11>=2.6.0
Requires-Dist: prometheus-client>=0.12.0
Requires-Dist: msgpack>=1.0.0
Requires-Dist: dill>=0.3.8
Requires-Dist: cloudpickle>=3.1.0
Requires-Dist: sortedcontainers>=2.4.0
Requires-Dist: numba==0.59.0; python_version == "3.9"
Requires-Dist: numba>=0.61.0; python_version >= "3.10" and python_version < "3.13"
Requires-Dist: pyston_lite_autoload>=2.3.5; python_version >= "3.9" and python_version <= "3.10" and sys_platform == "linux" and platform_machine == "x86_64"
Provides-Extra: dev
Requires-Dist: pytest<9,>=7.0; extra == "dev"
Requires-Dist: pytest-asyncio<0.26,>=0.21.0; extra == "dev"
Requires-Dist: pytest-cov>=4.0.0; extra == "dev"
Requires-Dist: pytest-xdist>=3.0.0; extra == "dev"
Requires-Dist: pytest-timeout>=2.3.1; extra == "dev"
Requires-Dist: pytest-benchmark>=4.0.0; extra == "dev"
Requires-Dist: hypothesis>=6.0.0; extra == "dev"
Requires-Dist: black<25,>=23.1.0; extra == "dev"
Requires-Dist: flake8<7,>=5.0.4; extra == "dev"
Requires-Dist: mypy<1.10,>=0.960; extra == "dev"
Requires-Dist: pre-commit>=2.17.0; extra == "dev"
Provides-Extra: test
Requires-Dist: pytest<9,>=7.0; extra == "test"
Requires-Dist: pytest-asyncio<0.26,>=0.21.0; extra == "test"
Requires-Dist: pytest-cov>=4.0.0; extra == "test"
Requires-Dist: pytest-xdist>=3.0.0; extra == "test"
Requires-Dist: pytest-timeout>=2.3.1; extra == "test"
Requires-Dist: pytest-benchmark>=4.0.0; extra == "test"
Requires-Dist: hypothesis>=6.0.0; extra == "test"
Requires-Dist: moto>=4.0.0; extra == "test"
Requires-Dist: toml>=0.10.2; extra == "test"
Requires-Dist: pandas<2.1.0,>=1.4.0; python_version == "3.9" and extra == "test"
Requires-Dist: pandas>=1.5.0; python_version >= "3.10" and extra == "test"
Requires-Dist: scipy<1.11.0,>=1.7.0; python_version == "3.9" and extra == "test"
Requires-Dist: scipy>=1.9.0; python_version >= "3.10" and extra == "test"
Requires-Dist: scikit-learn<1.4.0,>=1.1.0; python_version == "3.9" and extra == "test"
Requires-Dist: scikit-learn>=1.2.0; python_version >= "3.10" and extra == "test"
Requires-Dist: numba==0.59.0; python_version == "3.9" and extra == "test"
Requires-Dist: numba>=0.61.0; python_version >= "3.10" and extra == "test"
Requires-Dist: dash>=2.14.0; extra == "test"
Requires-Dist: dash-bootstrap-components>=1.0.0; extra == "test"
Requires-Dist: plotly>=5.0.0; extra == "test"
Requires-Dist: websockets>=13.0; extra == "test"
Requires-Dist: python-dotenv>=0.19.0; extra == "test"
Requires-Dist: requests>=2.25.0; extra == "test"
Requires-Dist: boto3>=1.20.0; extra == "test"
Dynamic: author
Dynamic: home-page
Dynamic: license-file
Dynamic: requires-python
